{
	"CONTROLS" : 
	[
		{
			"DEFAULT" : 0.5,
			"DESCRIPTION" : "",
			"MAX" : 1,
			"MIN" : -1,
			"NAME" : "rate_in",
			"TYPE" : "slider",
			"UI_GROUP" : "default"
		}
	],
	"CREDIT" : "Shane",
	"DESCRIPTION" : "Raymarched hexagonal Truchet tile, based off of Fabrice and Mattz's examples.",
	"GPU" : 0,
	"HEIGHT" : 1080,
	"IMAGE_PATH" : "raymarched_hexagonal_truchet.png",
	"MEDIA" : 
	[
		{
			"FILTER" : "linear",
			"WRAP" : "repeat"
		}
	],
	"TITLE" : "Raymarched Hexagonal Truchet",
	"WIDTH" : 1920
}