{
	"CONTROLS" : 
	[
		{
			"DEFAULT" : 0,
			"DESCRIPTION" : "",
			"MAX" : 1,
			"MIN" : 0,
			"NAME" : "auto_hue",
			"TYPE" : "toggle",
			"UI_GROUP" : "color"
		},
		{
			"DEFAULT" : 0,
			"DESCRIPTION" : "",
			"MAX" : 2,
			"MIN" : 0,
			"NAME" : "darker",
			"PARAMS" : 0.2,
			"TYPE" : "slider smooth",
			"UI_GROUP" : "color"
		},
		{
			"DEFAULT" : 0,
			"DESCRIPTION" : "",
			"MAX" : 1,
			"MIN" : 0,
			"NAME" : "flashing",
			"TYPE" : "toggle",
			"UI_GROUP" : "color"
		},
		{
			"DEFAULT" : 0.6,
			"DESCRIPTION" : "",
			"MAX" : 2,
			"MIN" : 0.25,
			"NAME" : "fov_mod",
			"PARAMS" : 0.022,
			"TYPE" : "slider smooth",
			"UI_GROUP" : "camera"
		},
		{
			"DEFAULT" : 
			[
				0,
				0
			],
			"DESCRIPTION" : "",
			"MAX" : 
			[
				1,
				1
			],
			"MIN" : 
			[
				-1,
				-1
			],
			"NAME" : "LookXY",
			"PARAMS" : 0.01,
			"TYPE" : "xy smooth",
			"UI_GROUP" : "camera"
		},
		{
			"DEFAULT" : 0,
			"DESCRIPTION" : "",
			"MAX" : 1,
			"MIN" : -1,
			"NAME" : "Spin",
			"PARAMS" : 0.046,
			"TYPE" : "knob smooth",
			"UI_GROUP" : "camera"
		},
		{
			"DEFAULT" : 0,
			"DESCRIPTION" : "",
			"MAX" : 1,
			"MIN" : -1,
			"NAME" : "FOV2",
			"PARAMS" : 0.118,
			"TYPE" : "slider smooth",
			"UI_GROUP" : "camera"
		},
		{
			"DEFAULT" : 1,
			"DESCRIPTION" : "",
			"MAX" : 1,
			"MIN" : 0,
			"NAME" : "ridges_constant",
			"TYPE" : "toggle",
			"UI_GROUP" : "shape"
		},
		{
			"DEFAULT" : 1,
			"DESCRIPTION" : "",
			"MAX" : -1,
			"MIN" : 1,
			"NAME" : "flatten",
			"PARAMS" : 0.025,
			"TYPE" : "slider smooth",
			"UI_GROUP" : "shape"
		},
		{
			"DEFAULT" : 0,
			"DESCRIPTION" : "",
			"MAX" : 1,
			"MIN" : 0,
			"NAME" : "highhits_ridges",
			"TYPE" : "toggle",
			"UI_GROUP" : "shape"
		},
		{
			"DEFAULT" : 0,
			"DESCRIPTION" : "",
			"MAX" : 1,
			"MIN" : 0,
			"NAME" : "spiral_ridges",
			"PARAMS" : 0.1,
			"TYPE" : "slider smooth",
			"UI_GROUP" : "shape"
		},
		{
			"DEFAULT" : 0.1,
			"DESCRIPTION" : "",
			"MAX" : 0.4,
			"MIN" : -0.4,
			"NAME" : "speed_direction",
			"PARAMS" : 0.01,
			"TYPE" : "knob traveler",
			"UI_GROUP" : "time"
		},
		{
			"DEFAULT" : 0.35,
			"DESCRIPTION" : "",
			"MAX" : 1,
			"MIN" : 0,
			"NAME" : "bass_time",
			"TYPE" : "knob",
			"UI_GROUP" : "time"
		},
		{
			"DEFAULT" : 0.5,
			"DESCRIPTION" : "",
			"MAX" : 2,
			"MIN" : 0,
			"NAME" : "media_scale",
			"PARAMS" : 0.01,
			"TYPE" : "slider smooth",
			"UI_GROUP" : "media"
		},
		{
			"DEFAULT" : 0,
			"DESCRIPTION" : "",
			"MAX" : 1,
			"MIN" : 0,
			"NAME" : "media_only",
			"PARAMS" : 0.1,
			"TYPE" : "slider smooth",
			"UI_GROUP" : "media"
		},
		{
			"DEFAULT" : 0,
			"DESCRIPTION" : "",
			"MAX" : 1,
			"MIN" : 0,
			"NAME" : "selector",
			"PARAMS" : 0.01,
			"TYPE" : "slider smooth",
			"UI_GROUP" : "media"
		},
		{
			"DEFAULT" : 
			[
				0,
				0
			],
			"DESCRIPTION" : "",
			"MAX" : 
			[
				1,
				1
			],
			"MIN" : 
			[
				0,
				0
			],
			"NAME" : "Warp",
			"PARAMS" : 0.125,
			"TYPE" : "xy smooth",
			"UI_GROUP" : "default"
		},
		{
			"DEFAULT" : 
			[
				0,
				0
			],
			"DESCRIPTION" : "",
			"MAX" : 
			[
				1,
				1
			],
			"MIN" : 
			[
				0,
				0
			],
			"NAME" : "Psp",
			"PARAMS" : 0.072,
			"TYPE" : "xy smooth",
			"UI_GROUP" : "default"
		}
	],
	"CREDIT" : "aiekick",
	"DESCRIPTION" : " Ray Marching Experiment 62 with another lighting try :)",
	"GPU" : 0,
	"HEIGHT" : 1440,
	"IMAGE_PATH" : "ray_marching_experiment_62_dup.png",
	"TITLE" : "Ray Marching Experiment 62_dup",
	"WIDTH" : 2560
}