{
	"CONTROLS" : 
	[
		{
			"DEFAULT" : 
			[
				0,
				0
			],
			"DESCRIPTION" : "",
			"MAX" : 
			[
				1,
				1
			],
			"MIN" : 
			[
				0,
				0
			],
			"NAME" : "MouseXY",
			"TYPE" : "xy",
			"UI_GROUP" : "defaults"
		},
		{
			"DEFAULT" : 0,
			"DESCRIPTION" : "",
			"MAX" : 1,
			"MIN" : 0,
			"NAME" : "MouseClick",
			"TYPE" : "toggle",
			"UI_GROUP" : "defaults"
		}
	],
	"CREDIT" : "aiekick",
	"DESCRIPTION" : "based on iq Apollonian [url=https://www.shadertoy.com/view/4ds3zn]Apollonian[/url]",
	"GPU" : 0,
	"HEIGHT" : 720,
	"IMAGE_PATH" : "iq_apollonian_fork.png",
	"TITLE" : "Iq Apollonian Fork",
	"WIDTH" : 1280
}